thoughtstorms/PageStore.py
thoughtstorms/SFWTools.py
thoughtstorms/__init__.py
thoughtstorms/legacy.py
thoughtstorms/txlib.py
thoughtstorms/utPageStore.py
thoughtstorms/utTxLib.py
thoughtstorms-0.0.63.dist-info/LICENSE.txt
thoughtstorms-0.0.63.dist-info/METADATA
thoughtstorms-0.0.63.dist-info/WHEEL
thoughtstorms-0.0.63.dist-info/top_level.txt
thoughtstorms-0.0.63.dist-info/RECORD
