Metadata-Version: 2.1
Name: thoughtstorms
Version: 0.0.63
Summary: Components from Project ThoughtStorms (ThoughtStorms wiki and associated software)
Home-page: https://github.com/interstar/ThoughtStorms
Author: Phil Jones
Author-email: interstar@gmail.com
License: MIT
Platform: UNKNOWN
Classifier: Development Status :: 3 - Alpha
Classifier: Intended Audience :: Developers
Requires-Dist: Markdown
Requires-Dist: PyYAML (>=3.12)
Requires-Dist: fsquery (>=0.2.0)
